askquinta/__init__.py
askquinta/ETL/NLP.py
askquinta/ETL/__init__.py
askquinta/blastmessage/Blast_Message.py
askquinta/blastmessage/__init__.py
askquinta/connector/API.py
askquinta/connector/ArangoDB.py
askquinta/connector/MySQL.py
askquinta/connector/__init__.py
askquinta/google/BQ.py
askquinta/google/Gsheet.py
askquinta/google/__init__.py
askquinta-2.0.7.dist-info/LICENSE
askquinta-2.0.7.dist-info/METADATA
askquinta-2.0.7.dist-info/WHEEL
askquinta-2.0.7.dist-info/top_level.txt
askquinta-2.0.7.dist-info/RECORD
