Metadata-Version: 2.1
Name: askquinta
Version: 2.0.7
Summary: Package for daily usage of data team at Paper.id
Home-page: https://github.com/paper-indonesia/composer
Author: Paper Data Team
Classifier: Programming Language :: Python :: 3
Classifier: License :: OSI Approved :: MIT License
Classifier: Operating System :: OS Independent
License-File: LICENSE
